dice_notation/__init__.py
dice_notation/algebra.py
dice_notation/dice.py
dice_notation/parser/DiceNotationLexer.py
dice_notation/parser/DiceNotationListener.py
dice_notation/parser/DiceNotationParser.py
dice_notation/parser/__init__.py
dice_notation/parser/dice.py
tests/__init__.py
tests/test_dice.py
tests/parser/__init__.py
tests/parser/test_dice_parser_invalid.py
tests/parser/dice/__init__.py
tests/parser/dice/test_dice_parser_dice.py
tests/parser/dice/test_dice_parser_dice_binary_operation.py
tests/parser/dice/test_dice_parser_dice_roll.py
tests/parser/number/__init__.py
tests/parser/number/test_dice_parser_number.py
tests/parser/number/test_dice_parser_number_add.py
tests/parser/number/test_dice_parser_number_binary_op_mixed.py
tests/parser/number/test_dice_parser_number_rollable.py
tests/parser/number/test_dice_parser_number_rollable_mixed.py
tests/parser/number/test_dice_parser_number_sub.py
dice_notation-1.2.1.dist-info/LICENSE
dice_notation-1.2.1.dist-info/METADATA
dice_notation-1.2.1.dist-info/WHEEL
dice_notation-1.2.1.dist-info/top_level.txt
dice_notation-1.2.1.dist-info/RECORD
