Metadata-Version: 2.1
Name: dice-notation
Version: 1.2.1
Summary: Dice notation tools
Home-page: https://github.com/Bernardo-MG/dice-notation-python
Author: Bernardo Martínez Garrido
Author-email: programming@bernardomg.com
License: MIT
Download-URL: https://pypi.python.org/pypi/dice-notation
Keywords: dice,dice notation,rpg,parser
Platform: any
Classifier: Development Status :: 5 - Production/Stable
Classifier: Intended Audience :: Developers
Classifier: License :: OSI Approved :: MIT License
Classifier: Programming Language :: Python
Classifier: Programming Language :: Python :: 3
Classifier: Programming Language :: Python :: 3.6
Classifier: Programming Language :: Python :: 3.7
Classifier: Programming Language :: Python :: 3.8
Classifier: Programming Language :: Python :: 3.9
Classifier: Topic :: Games/Entertainment :: Role-Playing
Requires-Python: >=3.6
License-File: LICENSE
Requires-Dist: antlr4-python3-runtime
Requires-Dist: bernardomg.tox-test-command
Requires-Dist: bernardomg.version-extractor
Provides-Extra: test
Requires-Dist: tox ; extra == 'test'
